jtech_robotframework_ai/__init__.py
jtech_robotframework_ai/agent.py
jtech_robotframework_ai/core.py
jtech_robotframework_ai/crew.py
jtech_robotframework_ai/metadata.py
jtech_robotframework_ai/task.py
jtech_robotframework_ai/tool.py
jtech_robotframework_ai/vertex.py
jtechrobotframeworkai-0.1.0.dist-info/METADATA
jtechrobotframeworkai-0.1.0.dist-info/WHEEL
jtechrobotframeworkai-0.1.0.dist-info/top_level.txt
jtechrobotframeworkai-0.1.0.dist-info/RECORD
