Metadata-Version: 2.4
Name: JTechRobotFrameworkAI
Version: 0.1.0
Summary: Uma biblioteca Robot Framework com recursos de IA usando Google Generative AI e CrewAI
Home-page: https://github.com/jtech-eng/jtech-robotframework-ai
Author: JTech
Author-email: JTech <angelo@jtech.eng.br>
License: MIT
Project-URL: Homepage, https://github.com/jtech-eng/jtech-robotframework-ai
Project-URL: Repository, https://github.com/jtech-eng/jtech-robotframework-ai.git
Classifier: Development Status :: 3 - Alpha
Classifier: Intended Audience :: Developers
Classifier: License :: OSI Approved :: MIT License
Classifier: Programming Language :: Python :: 3
Classifier: Programming Language :: Python :: 3.9
Classifier: Programming Language :: Python :: 3.10
Classifier: Programming Language :: Python :: 3.11
Classifier: Programming Language :: Python :: 3.12
Requires-Python: >=3.9
Requires-Dist: robotframework>=6.1.1
Requires-Dist: google-generativeai>=0.3.2
Requires-Dist: langchain>=0.1.0
Requires-Dist: langchain-google-genai>=0.0.5
Requires-Dist: crewai>=0.11.0
Requires-Dist: python-dotenv>=1.0.0
Requires-Dist: psycopg2-binary>=2.9.9
Requires-Dist: sqlalchemy>=2.0.0
Dynamic: author
Dynamic: home-page
Dynamic: requires-python
